django_simple_email_verification-0.1.2.dist-info/DESCRIPTION.rst
django_simple_email_verification-0.1.2.dist-info/METADATA
django_simple_email_verification-0.1.2.dist-info/RECORD
django_simple_email_verification-0.1.2.dist-info/WHEEL
django_simple_email_verification-0.1.2.dist-info/metadata.json
django_simple_email_verification-0.1.2.dist-info/top_level.txt
simple_email_verification/__init__.py
simple_email_verification/admin.py
simple_email_verification/apps.py
simple_email_verification/decorators.py
simple_email_verification/forms.py
simple_email_verification/models.py
simple_email_verification/send_confirmation.py
simple_email_verification/signals.py
simple_email_verification/views.py
simple_email_verification/migrations/0001_initial.py
simple_email_verification/migrations/__init__.py
simple_email_verification/templates/simple_email_verification/confirm.html
simple_email_verification/templates/simple_email_verification/confirm.txt
simple_email_verification/templates/simple_email_verification/verify.html
