Metadata-Version: 2.0
Name: django-simple-email-verification
Version: 0.1.2
Summary: A view decorator for verifying e-mail addresses
Home-page: https://github.com/musashiXXX/django-simple-email-verification
Author: Charles Hamilton
Author-email: musashi@nefaria.com
License: LICENSE.txt
Download-URL: https://github.com/musashiXXX/django-simple-email-verification/tarball/0.1.2
Keywords: email django
Platform: UNKNOWN
Requires-Dist: Django (>=1.8)
